rtl/nco_LUT.vhd
-- sin_lut stores quater-wave absolute amplitude values (0°~90°)
-- sin_abs, cos_abs outputs are absolute values only
-- sign and address folding is handled in upper NCO logic


library ieee;
use ieee.std_logic_1164.all;
use ieee.numeric_std.all;

entity nco_LUT is
    generic(
        ADDR_WIDTH  : integer := 6;
        OUT_WIDTH : integer := 16
    );
    port (
        clk : in std_logic;
        addr_sin : in unsigned(ADDR_WIDTH - 1 downto 0);
        addr_cos : in unsigned(ADDR_WIDTH - 1 downto 0);
        sin_abs : out signed(OUT_WIDTH - 1 downto 0);
        cos_abs : out signed(OUT_WIDTH - 1 downto 0)
    );
end entity;

architecture ROM of nco_LUT is
    type lut_type is array (0 to 2**(ADDR_WIDTH)-1) of signed(OUT_WIDTH - 1 downto 0);
    constant sin_lut : lut_type := (
         0 => signed'("0000000000000000"),
         1 => signed'("0000001100110000"),
         2 => signed'("0000011001100001"),
         3 => signed'("0000100110010000"),
         4 => signed'("0000110010111110"),
         5 => signed'("0000111111101010"),
         6 => signed'("0001001100010011"),
         7 => signed'("0001011000111001"),
         8 => signed'("0001100101011100"),
         9 => signed'("0001110001111011"),
        10 => signed'("0001111110010101"),
        11 => signed'("0010001010101010"),
        12 => signed'("0010010110111010"),
        13 => signed'("0010100011000011"),
        14 => signed'("0010101111000110"),
        15 => signed'("0010111011000011"),
        16 => signed'("0011000110110111"),
        17 => signed'("0011010010100100"),
        18 => signed'("0011011110001001"),
        19 => signed'("0011101001100100"),
        20 => signed'("0011110100110110"),
        21 => signed'("0011111111111111"),
        22 => signed'("0100001010111101"),
        23 => signed'("0100010101110001"),
        24 => signed'("0100100000011010"),
        25 => signed'("0100101010110111"),
        26 => signed'("0100110101001000"),
        27 => signed'("0100111111001101"),
        28 => signed'("0101001001000110"),
        29 => signed'("0101010010110001"),
        30 => signed'("0101011100001111"),
        31 => signed'("0101100101011111"),
        32 => signed'("0101101110100000"),
        33 => signed'("0101110111010011"),
        34 => signed'("0101111111111000"),
        35 => signed'("0110001000001100"),
        36 => signed'("0110010000010010"),
        37 => signed'("0110011000000111"),
        38 => signed'("0110011111101100"),
        39 => signed'("0110100111000001"),
        40 => signed'("0110101110000101"),
        41 => signed'("0110110100110111"),
        42 => signed'("0110111011011001"),
        43 => signed'("0111000001101000"),
        44 => signed'("0111000111100110"),
        45 => signed'("0111001101010010"),
        46 => signed'("0111010010101011"),
        47 => signed'("0111010111110010"),
        48 => signed'("0111011100100101"),
        49 => signed'("0111100001000110"),
        50 => signed'("0111100101010100"),
        51 => signed'("0111101001001111"),
        52 => signed'("0111101100110110"),
        53 => signed'("0111110000001001"),
        54 => signed'("0111110011001001"),
        55 => signed'("0111110101110101"),
        56 => signed'("0111111000001101"),
        57 => signed'("0111111010010001"),
        58 => signed'("0111111100000000"),
        59 => signed'("0111111101011100"),
        60 => signed'("0111111110100011"),
        61 => signed'("0111111111010110"),
        62 => signed'("0111111111110100"),
        63 => signed'("0111111111111111")
    );
    signal sin_abs_temp : signed(OUT_WIDTH - 1 downto 0):=(others => '0');
    signal cos_abs_temp : signed(OUT_WIDTH - 1 downto 0):=(others => '0');
begin

process(clk)
begin
    if rising_edge(clk) then
        sin_abs_temp <= sin_lut(to_integer(addr_sin));
        cos_abs_temp <= sin_lut(to_integer(addr_cos));
    end if;
end process;

sin_abs <= sin_abs_temp;
cos_abs <= cos_abs_temp;

end architecture;

sim/nco/nco_lut/wave.vcd
$date
  Fri Mar 13 14:53:51 2026
$end
$version
  GHDL v0
$end
$timescale
  1 ps
$end
$scope module standard $end
$upscope $end
$scope module textio $end
$upscope $end
$scope module std_logic_1164 $end
$upscope $end
$scope module numeric_std $end
$upscope $end
$scope module nco_lut $end
$var reg 1 ! clk $end
$var reg 6 " addr_sin[5:0] $end
$var reg 6 # addr_cos[5:0] $end
$var reg 16 $ sin_abs[15:0] $end
$var reg 16 % cos_abs[15:0] $end
$var reg 16 & sin_abs_temp[15:0] $end
$var reg 16 ' cos_abs_temp[15:0] $end
$upscope $end
$enddefinitions $end
#0
1!
b000000 "
b111111 #
b0000000000000000 $
b0000000000000000 %
b0000000000000000 &
b0000000000000000 '
#5000
0!
#10000
1!
b000001 "
b111110 #
b0111111111111111 %
b0111111111111111 '
#15000
0!
#20000
1!
b000010 "
b111101 #
b0000001100110000 $
b0111111111110100 %
b0000001100110000 &
b0111111111110100 '
#25000
0!
#30000
1!
b000011 "
b111100 #
b0000011001100001 $
b0111111111010110 %
b0000011001100001 &
b0111111111010110 '
#35000
0!
#40000
1!
b000100 "
b111011 #
b0000100110010000 $
b0111111110100011 %
b0000100110010000 &
b0111111110100011 '
#45000
0!
#50000
1!
b000101 "
b111010 #
b0000110010111110 $
b0111111101011100 %
b0000110010111110 &
b0111111101011100 '
#55000
0!
#60000
1!
b000110 "
b111001 #
b0000111111101010 $
b0111111100000000 %
b0000111111101010 &
b0111111100000000 '
#65000
0!
#70000
1!
b000111 "
b111000 #
b0001001100010011 $
b0111111010010001 %
b0001001100010011 &
b0111111010010001 '
#75000
0!
#80000
1!
b001000 "
b110111 #
b0001011000111001 $
b0111111000001101 %
b0001011000111001 &
b0111111000001101 '
#85000
0!
#90000
1!
b001001 "
b110110 #
b0001100101011100 $
b0111110101110101 %
b0001100101011100 &
b0111110101110101 '
#95000
0!
#100000
1!
b001010 "
b110101 #
b0001110001111011 $
b0111110011001001 %
b0001110001111011 &
b0111110011001001 '
#105000
0!
#110000
1!
b001011 "
b110100 #
b0001111110010101 $
b0111110000001001 %
b0001111110010101 &
b0111110000001001 '
#115000
0!
#120000
1!
b001100 "
b110011 #
b0010001010101010 $
b0111101100110110 %
b0010001010101010 &
b0111101100110110 '
#125000
0!
#130000
1!
b001101 "
b110010 #
b0010010110111010 $
b0111101001001111 %
b0010010110111010 &
b0111101001001111 '
#135000
0!
#140000
1!
b001110 "
b110001 #
b0010100011000011 $
b0111100101010100 %
b0010100011000011 &
b0111100101010100 '
#145000
0!
#150000
1!
b001111 "
b110000 #
b0010101111000110 $
b0111100001000110 %
b0010101111000110 &
b0111100001000110 '
#155000
0!
#160000
1!
b010000 "
b101111 #
b0010111011000011 $
b0111011100100101 %
b0010111011000011 &
b0111011100100101 '
#165000
0!
#170000
1!
b010001 "
b101110 #
b0011000110110111 $
b0111010111110010 %
b0011000110110111 &
b0111010111110010 '
#175000
0!
#180000
1!
b010010 "
b101101 #
b0011010010100100 $
b0111010010101011 %
b0011010010100100 &
b0111010010101011 '
#185000
0!
#190000
1!
b010011 "
b101100 #
b0011011110001001 $
b0111001101010010 %
b0011011110001001 &
b0111001101010010 '
#195000
0!
#200000
1!
b010100 "
b101011 #
b0011101001100100 $
b0111000111100110 %
b0011101001100100 &
b0111000111100110 '
#205000
0!
#210000
1!
b010101 "
b101010 #
b0011110100110110 $
b0111000001101000 %
b0011110100110110 &
b0111000001101000 '
#215000
0!
#220000
1!
b010110 "
b101001 #
b0011111111111111 $
b0110111011011001 %
b0011111111111111 &
b0110111011011001 '
#225000
0!
#230000
1!
b010111 "
b101000 #
b0100001010111101 $
b0110110100110111 %
b0100001010111101 &
b0110110100110111 '
#235000
0!
#240000
1!
b011000 "
b100111 #
b0100010101110001 $
b0110101110000101 %
b0100010101110001 &
b0110101110000101 '
#245000
0!
#250000
1!
b011001 "
b100110 #
b0100100000011010 $
b0110100111000001 %
b0100100000011010 &
b0110100111000001 '
#255000
0!
#260000
1!
b011010 "
b100101 #
b0100101010110111 $
b0110011111101100 %
b0100101010110111 &
b0110011111101100 '
#265000
0!
#270000
1!
b011011 "
b100100 #
b0100110101001000 $
b0110011000000111 %
b0100110101001000 &
b0110011000000111 '
#275000
0!
#280000
1!
b011100 "
b100011 #
b0100111111001101 $
b0110010000010010 %
b0100111111001101 &
b0110010000010010 '
#285000
0!
#290000
1!
b011101 "
b100010 #
b0101001001000110 $
b0110001000001100 %
b0101001001000110 &
b0110001000001100 '
#295000
0!
#300000
1!
b011110 "
b100001 #
b0101010010110001 $
b0101111111111000 %
b0101010010110001 &
b0101111111111000 '
#305000
0!
#310000
1!
b011111 "
b100000 #
b0101011100001111 $
b0101110111010011 %
b0101011100001111 &
b0101110111010011 '
#315000
0!
#320000
1!
b100000 "
b011111 #
b0101100101011111 $
b0101101110100000 %
b0101100101011111 &
b0101101110100000 '
#325000
0!
#330000
1!
b100001 "
b011110 #
b0101101110100000 $
b0101100101011111 %
b0101101110100000 &
b0101100101011111 '
#335000
0!
#340000
1!
b100010 "
b011101 #
b0101110111010011 $
b0101011100001111 %
b0101110111010011 &
b0101011100001111 '
#345000
0!
#350000
1!
b100011 "
b011100 #
b0101111111111000 $
b0101010010110001 %
b0101111111111000 &
b0101010010110001 '
#355000
0!
#360000
1!
b100100 "
b011011 #
b0110001000001100 $
b0101001001000110 %
b0110001000001100 &
b0101001001000110 '
#365000
0!
#370000
1!
b100101 "
b011010 #
b0110010000010010 $
b0100111111001101 %
b0110010000010010 &
b0100111111001101 '
#375000
0!
#380000
1!
b100110 "
b011001 #
b0110011000000111 $
b0100110101001000 %
b0110011000000111 &
b0100110101001000 '
#385000
0!
#390000
1!
b100111 "
b011000 #
b0110011111101100 $
b0100101010110111 %
b0110011111101100 &
b0100101010110111 '
#395000
0!
#400000
1!
b101000 "
b010111 #
b0110100111000001 $
b0100100000011010 %
b0110100111000001 &
b0100100000011010 '
#405000
0!
#410000
1!
b101001 "
b010110 #
b0110101110000101 $
b0100010101110001 %
b0110101110000101 &
b0100010101110001 '
#415000
0!
#420000
1!
b101010 "
b010101 #
b0110110100110111 $
b0100001010111101 %
b0110110100110111 &
b0100001010111101 '
#425000
0!
#430000
1!
b101011 "
b010100 #
b0110111011011001 $
b0011111111111111 %
b0110111011011001 &
b0011111111111111 '
#435000
0!
#440000
1!
b101100 "
b010011 #
b0111000001101000 $
b0011110100110110 %
b0111000001101000 &
b0011110100110110 '
#445000
0!
#450000
1!
b101101 "
b010010 #
b0111000111100110 $
b0011101001100100 %
b0111000111100110 &
b0011101001100100 '
#455000
0!
#460000
1!
b101110 "
b010001 #
b0111001101010010 $
b0011011110001001 %
b0111001101010010 &
b0011011110001001 '
#465000
0!
#470000
1!
b101111 "
b010000 #
b0111010010101011 $
b0011010010100100 %
b0111010010101011 &
b0011010010100100 '
#475000
0!
#480000
1!
b110000 "
b001111 #
b0111010111110010 $
b0011000110110111 %
b0111010111110010 &
b0011000110110111 '
#485000
0!
#490000
1!
b110001 "
b001110 #
b0111011100100101 $
b0010111011000011 %
b0111011100100101 &
b0010111011000011 '
#495000
0!
#500000
1!
b110010 "
b001101 #
b0111100001000110 $
b0010101111000110 %
b0111100001000110 &
b0010101111000110 '
#505000
0!
#510000
1!
b110011 "
b001100 #
b0111100101010100 $
b0010100011000011 %
b0111100101010100 &
b0010100011000011 '
#515000
0!
#520000
1!
b110100 "
b001011 #
b0111101001001111 $
b0010010110111010 %
b0111101001001111 &
b0010010110111010 '
#525000
0!
#530000
1!
b110101 "
b001010 #
b0111101100110110 $
b0010001010101010 %
b0111101100110110 &
b0010001010101010 '
#535000
0!
#540000
1!
b110110 "
b001001 #
b0111110000001001 $
b0001111110010101 %
b0111110000001001 &
b0001111110010101 '
#545000
0!
#550000
1!
b110111 "
b001000 #
b0111110011001001 $
b0001110001111011 %
b0111110011001001 &
b0001110001111011 '
#555000
0!
#560000
1!
b111000 "
b000111 #
b0111110101110101 $
b0001100101011100 %
b0111110101110101 &
b0001100101011100 '
#565000
0!
#570000
1!
b111001 "
b000110 #
b0111111000001101 $
b0001011000111001 %
b0111111000001101 &
b0001011000111001 '
#575000
0!
#580000
1!
b111010 "
b000101 #
b0111111010010001 $
b0001001100010011 %
b0111111010010001 &
b0001001100010011 '
#585000
0!
#590000
1!
b111011 "
b000100 #
b0111111100000000 $
b0000111111101010 %
b0111111100000000 &
b0000111111101010 '
#595000
0!
#600000
1!
b111100 "
b000011 #
b0111111101011100 $
b0000110010111110 %
b0111111101011100 &
b0000110010111110 '
#605000
0!
#610000
1!
b111101 "
b000010 #
b0111111110100011 $
b0000100110010000 %
b0111111110100011 &
b0000100110010000 '
#615000
0!
#620000
1!
b111110 "
b000001 #
b0111111111010110 $
b0000011001100001 %
b0111111111010110 &
b0000011001100001 '
#625000
0!
#630000
1!
b111111 "
b000000 #
b0111111111110100 $
b0000001100110000 %
b0111111111110100 &
b0000001100110000 '
#635000
0!
#640000
1!
b0111111111111111 $
b0000000000000000 %
b0111111111111111 &
b0000000000000000 '
